piglet/__init__.py
piglet/__main__.py
piglet/cli.py
piglet/client.py
piglet/config.py
piglet/exceptions.py
piglet/helpers.py
piglet/output.py
piglet/commands/__init__.py
piglet/commands/cohorts.py
piglet/commands/dashboards.py
piglet/commands/flags.py
piglet/commands/insights.py
piglet/commands/projects.py
cased_piglet-0.1.0.dist-info/METADATA
cased_piglet-0.1.0.dist-info/WHEEL
cased_piglet-0.1.0.dist-info/entry_points.txt
cased_piglet-0.1.0.dist-info/licenses/LICENSE
cased_piglet-0.1.0.dist-info/RECORD
